VeeamOneAPI/Functions.py
VeeamOneAPI/__init__.py
VeeamOneAPIWrapper/Functions.py
VeeamOneAPIWrapper/__init__.py
VeeamOneAPIWrapper-0.0.4.dist-info/METADATA
VeeamOneAPIWrapper-0.0.4.dist-info/WHEEL
VeeamOneAPIWrapper-0.0.4.dist-info/top_level.txt
VeeamOneAPIWrapper-0.0.4.dist-info/RECORD
