Metadata-Version: 2.1
Name: VeeamOneAPIWrapper
Version: 0.0.4
Summary: Veeam One API Python Wrapper
Author: HHaustreis
Author-email: <henrik@haustreis.onmicrosoft.com>
License: UNKNOWN
Keywords: python,API,Veeam,One,VeeamOne
Platform: UNKNOWN
Classifier: Development Status :: 1 - Planning
Classifier: Intended Audience :: Developers
Classifier: Programming Language :: Python :: 3
Classifier: Operating System :: Unix
Classifier: Operating System :: MacOS :: MacOS X
Classifier: Operating System :: Microsoft :: Windows
Requires-Dist: VeeamOneAPIWrapper
